{ "hubs":[
	"Belo Horizonte",
	"Juiz de Fora",
	"Montes Claros",
	"Ipatinga",
	"Betim",
	"Araguari",
	"Uberaba",
	"Presidente Olegário",
	"Elói Mendes"
],
"ligacoes":[
	{"no":"Uberlândia", "concentrador":"Araguari"},
	{"no":"Contagem", "concentrador":"Belo Horizonte"},
	{"no":"Sete Lagoas", "concentrador":"Belo Horizonte"},
	{"no":"Nova Lima", "concentrador":"Belo Horizonte"},
	{"no":"Poços de Caldas", "concentrador":"Elói Mendes"},
	{"no":"Ouro Preto", "concentrador":"Belo Horizonte"},
	{"no":"Itabira", "concentrador":"Belo Horizonte"},
	{"no":"Varginha", "concentrador":"Elói Mendes"},
	{"no":"Mariana", "concentrador":"Belo Horizonte"},
	{"no":"Divinópolis", "concentrador":"Betim"},
	{"no":"Pouso Alegre", "concentrador":"Elói Mendes"},
	{"no":"Governador Valadares", "concentrador":"Ipatinga"},
	{"no":"Extrema", "concentrador":"Elói Mendes"},
	{"no":"Araxá", "concentrador":"Uberaba"},
	{"no":"Ribeirão das Neves", "concentrador":"Belo Horizonte"},
	{"no":"Patos de Minas", "concentrador":"Presidente Olegário"},
	{"no":"Santa Luzia", "concentrador":"Belo Horizonte"},
	{"no":"Congonhas", "concentrador":"Belo Horizonte"},
	{"no":"Paracatu", "concentrador":"Presidente Olegário"},
	{"no":"São Gonçalo do Rio Abaixo", "concentrador":"Belo Horizonte"},
	{"no":"Ouro Branco", "concentrador":"Belo Horizonte"},
	{"no":"Itabirito", "concentrador":"Belo Horizonte"},
	{"no":"Ituiutaba", "concentrador":"Araguari"},
	{"no":"Unaí", "concentrador":"Presidente Olegário"},
	{"no":"Três Corações", "concentrador":"Elói Mendes"},
	{"no":"Patrocínio", "concentrador":"Presidente Olegário"},
	{"no":"Timóteo", "concentrador":"Ipatinga"},
	{"no":"Vespasiano", "concentrador":"Belo Horizonte"},
	{"no":"Guaxupé", "concentrador":"Elói Mendes"},
	{"no":"Pará de Minas", "concentrador":"Betim"},
	{"no":"Brumadinho", "concentrador":"Betim"},
	{"no":"Itaúna", "concentrador":"Betim"},
	{"no":"Itajubá", "concentrador":"Elói Mendes"},
	{"no":"Passos", "concentrador":"Elói Mendes"},
	{"no":"Barbacena", "concentrador":"Juiz de Fora"},
	{"no":"João Monlevade", "concentrador":"Belo Horizonte"},
	{"no":"Confins", "concentrador":"Belo Horizonte"},
	{"no":"Alfenas", "concentrador":"Elói Mendes"},
	{"no":"Lavras", "concentrador":"Elói Mendes"},
	{"no":"Ubá", "concentrador":"Juiz de Fora"},
	{"no":"Sabará", "concentrador":"Belo Horizonte"},
	{"no":"Teófilo Otoni", "concentrador":"Ipatinga"},
	{"no":"Ibirité", "concentrador":"Belo Horizonte"},
	{"no":"Manhuaçu", "concentrador":"Ipatinga"},
	{"no":"Conselheiro Lafaiete", "concentrador":"Belo Horizonte"},
	{"no":"Muriaé", "concentrador":"Juiz de Fora"},
	{"no":"São Sebastião do Paraíso", "concentrador":"Elói Mendes"},
	{"no":"Frutal", "concentrador":"Uberaba"},
	{"no":"São João del Rei", "concentrador":"Belo Horizonte"},
	{"no":"Pirapora", "concentrador":"Montes Claros"},
	{"no":"Pedro Leopoldo", "concentrador":"Belo Horizonte"},
	{"no":"Itatiaiuçu", "concentrador":"Betim"},
	{"no":"Nova Serrana", "concentrador":"Betim"},
	{"no":"Araporã", "concentrador":"Araguari"},
	{"no":"Lagoa Santa", "concentrador":"Belo Horizonte"},
	{"no":"Caratinga", "concentrador":"Ipatinga"},
	{"no":"Coronel Fabriciano", "concentrador":"Ipatinga"},
	{"no":"Ponte Nova", "concentrador":"Belo Horizonte"},
	{"no":"Cataguases", "concentrador":"Juiz de Fora"},
	{"no":"Formiga", "concentrador":"Betim"},
	{"no":"Monte Carmelo", "concentrador":"Araguari"},
	{"no":"Santa Rita do Sapucaí", "concentrador":"Elói Mendes"},
	{"no":"Curvelo", "concentrador":"Belo Horizonte"},
	{"no":"Fronteira", "concentrador":"Uberaba"},
	{"no":"João Pinheiro", "concentrador":"Presidente Olegário"},
	{"no":"Viçosa", "concentrador":"Juiz de Fora"},
	{"no":"Lagoa da Prata", "concentrador":"Betim"},
	{"no":"Três Marias", "concentrador":"Presidente Olegário"},
	{"no":"Três Pontas", "concentrador":"Elói Mendes"},
	{"no":"Barão de Cocais", "concentrador":"Belo Horizonte"},
	{"no":"Iturama", "concentrador":"Uberaba"},
	{"no":"Juatuba", "concentrador":"Betim"},
	{"no":"Machado", "concentrador":"Elói Mendes"},
	{"no":"Arcos", "concentrador":"Betim"},
	{"no":"Conceição das Alagoas", "concentrador":"Uberaba"},
	{"no":"Piumhi", "concentrador":"Betim"},
	{"no":"Matozinhos", "concentrador":"Belo Horizonte"},
	{"no":"Além Paraíba", "concentrador":"Juiz de Fora"},
	{"no":"Bom Despacho", "concentrador":"Betim"},
	{"no":"Visconde do Rio Branco", "concentrador":"Juiz de Fora"},
	{"no":"Sacramento", "concentrador":"Uberaba"},
	{"no":"Boa Esperança", "concentrador":"Elói Mendes"},
	{"no":"Ibiá", "concentrador":"Presidente Olegário"},
	{"no":"Perdizes", "concentrador":"Uberaba"},
	{"no":"Coromandel", "concentrador":"Presidente Olegário"},
	{"no":"Janaúba", "concentrador":"Montes Claros"},
	{"no":"Leopoldina", "concentrador":"Juiz de Fora"},
	{"no":"Campo Belo", "concentrador":"Betim"},
	{"no":"Igarapé", "concentrador":"Betim"},
	{"no":"Várzea da Palma", "concentrador":"Montes Claros"},
	{"no":"Prata", "concentrador":"Araguari"},
	{"no":"Andradas", "concentrador":"Elói Mendes"},
	{"no":"Ibiraci", "concentrador":"Uberaba"},
	{"no":"Nova Ponte", "concentrador":"Uberaba"},
	{"no":"Buritis", "concentrador":"Presidente Olegário"},
	{"no":"Santos Dumont", "concentrador":"Juiz de Fora"},
	{"no":"Belo Oriente", "concentrador":"Ipatinga"},
	{"no":"Sarzedo", "concentrador":"Betim"},
	{"no":"São Lourenço", "concentrador":"Elói Mendes"},
	{"no":"São Gotardo", "concentrador":"Presidente Olegário"},
	{"no":"Carmo do Paranaíba", "concentrador":"Presidente Olegário"},
	{"no":"Santa Bárbara", "concentrador":"Ipatinga"},
	{"no":"Santa Vitória", "concentrador":"Araguari"},
	{"no":"Ouro Fino", "concentrador":"Elói Mendes"},
	{"no":"Matias Barbosa", "concentrador":"Juiz de Fora"},
	{"no":"Oliveira", "concentrador":"Betim"},
	{"no":"Bocaiúva", "concentrador":"Montes Claros"},
	{"no":"Cambuí", "concentrador":"Elói Mendes"},
	{"no":"Nanuque", "concentrador":"Ipatinga"},
	{"no":"Rio Paranaíba", "concentrador":"Presidente Olegário"},
	{"no":"Itaú de Minas", "concentrador":"Elói Mendes"},
	{"no":"Pompéu", "concentrador":"Betim"},
	{"no":"Guanhães", "concentrador":"Ipatinga"},
	{"no":"Diamantina", "concentrador":"Belo Horizonte"},
	{"no":"São João Batista do Glória", "concentrador":"Elói Mendes"},
	{"no":"Santa Juliana", "concentrador":"Uberaba"},
	{"no":"São Gonçalo do Sapucaí", "concentrador":"Elói Mendes"},
	{"no":"Mateus Leme", "concentrador":"Betim"},
	{"no":"Januária", "concentrador":"Montes Claros"},
	{"no":"Monte Alegre de Minas", "concentrador":"Araguari"},
	{"no":"Campina Verde", "concentrador":"Uberaba"},
	{"no":"Esmeraldas", "concentrador":"Belo Horizonte"},
	{"no":"São José da Barra", "concentrador":"Elói Mendes"},
	{"no":"Tupaciguara", "concentrador":"Araguari"},
	{"no":"Rio Piracicaba", "concentrador":"Belo Horizonte"},
	{"no":"Planura", "concentrador":"Uberaba"},
	{"no":"Caeté", "concentrador":"Belo Horizonte"},
	{"no":"Vazante", "concentrador":"Presidente Olegário"},
	{"no":"Campos Gerais", "concentrador":"Elói Mendes"},
	{"no":"Bambuí", "concentrador":"Betim"},
	{"no":"Indianópolis", "concentrador":"Araguari"},
	{"no":"Itamonte", "concentrador":"Elói Mendes"},
	{"no":"São Joaquim de Bicas", "concentrador":"Betim"},
	{"no":"Jacutinga", "concentrador":"Elói Mendes"},
	{"no":"Jaíba", "concentrador":"Montes Claros"},
	{"no":"Nepomuceno", "concentrador":"Elói Mendes"},
	{"no":"Itapagipe", "concentrador":"Uberaba"},
	{"no":"Itanhandu", "concentrador":"Elói Mendes"},
	{"no":"Cláudio", "concentrador":"Betim"},
	{"no":"Manhumirim", "concentrador":"Ipatinga"},
	{"no":"Salinas", "concentrador":"Montes Claros"},
	{"no":"Carandaí", "concentrador":"Belo Horizonte"},
	{"no":"Capelinha", "concentrador":"Montes Claros"},
	{"no":"Grão Mogol", "concentrador":"Montes Claros"},
	{"no":"Serra do Salitre", "concentrador":"Presidente Olegário"},
	{"no":"Monte Santo de Minas", "concentrador":"Elói Mendes"},
	{"no":"Paraopeba", "concentrador":"Belo Horizonte"},
	{"no":"Muzambinho", "concentrador":"Elói Mendes"},
	{"no":"São José da Lapa", "concentrador":"Belo Horizonte"},
	{"no":"Campo Florido", "concentrador":"Uberaba"},
	{"no":"Santo Antônio do Monte", "concentrador":"Betim"},
	{"no":"Carmo do Rio Claro", "concentrador":"Elói Mendes"},
	{"no":"Perdões", "concentrador":"Elói Mendes"},
	{"no":"Carangola", "concentrador":"Ipatinga"},
	{"no":"Santana do Paraíso", "concentrador":"Ipatinga"},
	{"no":"Luz", "concentrador":"Betim"},
	{"no":"Canápolis", "concentrador":"Araguari"},
	{"no":"Paraguaçu", "concentrador":"Elói Mendes"},
	{"no":"São Francisco", "concentrador":"Juiz de Fora"},
	{"no":"Guaranésia", "concentrador":"Elói Mendes"},
	{"no":"Aimorés", "concentrador":"Ipatinga"},
	{"no":"Tapira", "concentrador":"Uberaba"},
	{"no":"Itamarandiba", "concentrador":"Ipatinga"},
	{"no":"Camanducaia", "concentrador":"Elói Mendes"},
	{"no":"Pedra Azul", "concentrador":"Montes Claros"},
	{"no":"Almenara", "concentrador":"Montes Claros"},
	{"no":"Nova Resende", "concentrador":"Elói Mendes"},
	{"no":"Espera Feliz", "concentrador":"Ipatinga"},
	{"no":"Pitangui", "concentrador":"Betim"},
	{"no":"Paraisópolis", "concentrador":"Elói Mendes"},
	{"no":"Abaeté", "concentrador":"Betim"},
	{"no":"Ijaci", "concentrador":"Elói Mendes"},
	{"no":"Nova Era", "concentrador":"Ipatinga"},
	{"no":"Catas Altas", "concentrador":"Belo Horizonte"},
	{"no":"Monte Sião", "concentrador":"Elói Mendes"},
	{"no":"Campestre", "concentrador":"Elói Mendes"},
	{"no":"Barroso", "concentrador":"Juiz de Fora"},
	{"no":"Taiobeiras", "concentrador":"Montes Claros"},
	{"no":"Pirapetinga", "concentrador":"Juiz de Fora"},
	{"no":"Cássia", "concentrador":"Uberaba"},
	{"no":"Buritizeiro", "concentrador":"Montes Claros"},
	{"no":"Carlos Chagas", "concentrador":"Ipatinga"},
	{"no":"Campos Altos", "concentrador":"Betim"},
	{"no":"Alpinópolis", "concentrador":"Elói Mendes"},
	{"no":"Guarda-Mor", "concentrador":"Presidente Olegário"},
	{"no":"Iguatama", "concentrador":"Betim"},
	{"no":"Mantena", "concentrador":"Ipatinga"},
	{"no":"São Sebastião do Oeste", "concentrador":"Betim"},
	{"no":"Mutum", "concentrador":"Ipatinga"},
	{"no":"Itapecerica", "concentrador":"Betim"},
	{"no":"Fortaleza de Minas", "concentrador":"Elói Mendes"},
	{"no":"Corinto", "concentrador":"Belo Horizonte"},
	{"no":"Delta", "concentrador":"Uberaba"},
	{"no":"Carmópolis de Minas", "concentrador":"Betim"},
	{"no":"Capinópolis", "concentrador":"Araguari"},
	{"no":"São João Nepomuceno", "concentrador":"Juiz de Fora"},
	{"no":"Lagoa Formosa", "concentrador":"Presidente Olegário"},
	{"no":"Carmo do Cajuru", "concentrador":"Betim"},
	{"no":"Conselheiro Pena", "concentrador":"Ipatinga"},
	{"no":"Araçuaí", "concentrador":"Montes Claros"},
	{"no":"Passa Quatro", "concentrador":"Elói Mendes"},
	{"no":"Estrela do Sul", "concentrador":"Araguari"},
	{"no":"Jeceaba", "concentrador":"Belo Horizonte"},
	{"no":"Arceburgo", "concentrador":"Elói Mendes"},
	{"no":"Bom Sucesso", "concentrador":"Betim"},
	{"no":"Limeira do Oeste", "concentrador":"Uberaba"},
	{"no":"Lajinha", "concentrador":"Ipatinga"},
	{"no":"Rio Pardo de Minas", "concentrador":"Montes Claros"},
	{"no":"Capitão Enéas", "concentrador":"Montes Claros"},
	{"no":"Cabo Verde", "concentrador":"Elói Mendes"},
	{"no":"Carneirinho", "concentrador":"Uberaba"},
	{"no":"Lambari", "concentrador":"Elói Mendes"},
	{"no":"Porteirinha", "concentrador":"Montes Claros"},
	{"no":"Caxambu", "concentrador":"Elói Mendes"},
	{"no":"Raul Soares", "concentrador":"Ipatinga"},
	{"no":"Campanha", "concentrador":"Elói Mendes"},
	{"no":"Brasília de Minas", "concentrador":"Montes Claros"},
	{"no":"Santana da Vargem", "concentrador":"Elói Mendes"},
	{"no":"Inhapim", "concentrador":"Ipatinga"},
	{"no":"Pirajuba", "concentrador":"Uberaba"},
	{"no":"Francisco Sá", "concentrador":"Montes Claros"},
	{"no":"Pains", "concentrador":"Betim"},
	{"no":"Felixlândia", "concentrador":"Belo Horizonte"},
	{"no":"Conquista", "concentrador":"Uberaba"},
	{"no":"Monte Belo", "concentrador":"Elói Mendes"},
	{"no":"Brasilândia de Minas", "concentrador":"Presidente Olegário"},
	{"no":"Turmalina", "concentrador":"Montes Claros"},
	{"no":"Martinho Campos", "concentrador":"Betim"},
	{"no":"Resplendor", "concentrador":"Ipatinga"},
	{"no":"Espinosa", "concentrador":"Montes Claros"},
	{"no":"Divino", "concentrador":"Ipatinga"},
	{"no":"Candeias", "concentrador":"Elói Mendes"},
	{"no":"Santo Antônio do Amparo", "concentrador":"Betim"},
	{"no":"Rio Pomba", "concentrador":"Juiz de Fora"},
	{"no":"Poço Fundo", "concentrador":"Elói Mendes"},
	{"no":"Borda da Mata", "concentrador":"Elói Mendes"},
	{"no":"Coração de Jesus", "concentrador":"Montes Claros"},
	{"no":"Matipó", "concentrador":"Ipatinga"},
	{"no":"Iraí de Minas", "concentrador":"Araguari"},
	{"no":"Itambacuri", "concentrador":"Ipatinga"},
	{"no":"Minas Novas", "concentrador":"Montes Claros"},
	{"no":"Astolfo Dutra", "concentrador":"Juiz de Fora"},
	{"no":"Itamogi", "concentrador":"Elói Mendes"},
	{"no":"Itaobim", "concentrador":"Ipatinga"},
	{"no":"Conceição do Mato Dentro", "concentrador":"Belo Horizonte"},
	{"no":"Ervália", "concentrador":"Juiz de Fora"},
	{"no":"Bela Vista de Minas", "concentrador":"Belo Horizonte"},
	{"no":"Urucânia", "concentrador":"Ipatinga"},
	{"no":"Ipanema", "concentrador":"Ipatinga"},
	{"no":"Caldas", "concentrador":"Elói Mendes"},
	{"no":"Baependi", "concentrador":"Elói Mendes"},
	{"no":"Carmo da Cachoeira", "concentrador":"Elói Mendes"},
	{"no":"Lagoa Grande", "concentrador":"Presidente Olegário"},
	{"no":"Nazareno", "concentrador":"Betim"},
	{"no":"Alvinópolis", "concentrador":"Belo Horizonte"},
	{"no":"São Francisco de Sales", "concentrador":"Uberaba"},
	{"no":"Botelhos", "concentrador":"Elói Mendes"},
	{"no":"Carmo de Minas", "concentrador":"Elói Mendes"},
	{"no":"Areado", "concentrador":"Elói Mendes"},
	{"no":"Novo Cruzeiro", "concentrador":"Ipatinga"},
	{"no":"Arinos", "concentrador":"Montes Claros"},
	{"no":"Lima Duarte", "concentrador":"Juiz de Fora"},
	{"no":"Tocantins", "concentrador":"Juiz de Fora"},
	{"no":"Centralina", "concentrador":"Araguari"},
	{"no":"Santa Margarida", "concentrador":"Ipatinga"},
	{"no":"Dores de Campos", "concentrador":"Juiz de Fora"},
	{"no":"Cachoeira de Minas", "concentrador":"Elói Mendes"},
	{"no":"Guapé", "concentrador":"Elói Mendes"},
	{"no":"Papagaios", "concentrador":"Betim"},
	{"no":"Cristais", "concentrador":"Elói Mendes"},
	{"no":"São Domingos do Prata", "concentrador":"Ipatinga"},
	{"no":"Miraí", "concentrador":"Juiz de Fora"},
	{"no":"Conceição da Aparecida", "concentrador":"Elói Mendes"},
	{"no":"Itaguara", "concentrador":"Betim"},
	{"no":"Serro", "concentrador":"Belo Horizonte"},
	{"no":"Conceição do Rio Verde", "concentrador":"Elói Mendes"},
	{"no":"Alterosa", "concentrador":"Elói Mendes"},
	{"no":"Brasópolis", "concentrador":"Elói Mendes"},
	{"no":"Tiros", "concentrador":"Presidente Olegário"},
	{"no":"Cabeceira Grande", "concentrador":"Presidente Olegário"},
	{"no":"Lassance", "concentrador":"Belo Horizonte"},
	{"no":"Jequitinhonha", "concentrador":"Ipatinga"},
	{"no":"Água Comprida", "concentrador":"Uberaba"},
	{"no":"Conceição do Pará", "concentrador":"Betim"},
	{"no":"Simonésia", "concentrador":"Ipatinga"},
	{"no":"São João da Ponte", "concentrador":"Montes Claros"},
	{"no":"Monsenhor Paulo", "concentrador":"Elói Mendes"},
	{"no":"Medina", "concentrador":"Montes Claros"},
	{"no":"Dores do Indaiá", "concentrador":"Betim"},
	{"no":"Delfinópolis", "concentrador":"Uberaba"},
	{"no":"Águas Formosas", "concentrador":"Ipatinga"},
	{"no":"Rodeiro", "concentrador":"Juiz de Fora"},
	{"no":"Bicas", "concentrador":"Juiz de Fora"},
	{"no":"Cruzília", "concentrador":"Elói Mendes"},
	{"no":"Rio Casca", "concentrador":"Ipatinga"},
	{"no":"Itacarambi", "concentrador":"Montes Claros"},
	{"no":"Formoso", "concentrador":"Presidente Olegário"},
	{"no":"Ilicínea", "concentrador":"Elói Mendes"},
	{"no":"São João do Paraíso", "concentrador":"Montes Claros"},
	{"no":"Pimenta", "concentrador":"Betim"},
	{"no":"Romaria", "concentrador":"Araguari"},
	{"no":"Monte Azul", "concentrador":"Montes Claros"},
	{"no":"Cambuquira", "concentrador":"Elói Mendes"},
	{"no":"Antônio Carlos", "concentrador":"Juiz de Fora"},
	{"no":"Jaboticatubas", "concentrador":"Belo Horizonte"},
	{"no":"Passa Tempo", "concentrador":"Betim"},
	{"no":"Juruaia", "concentrador":"Elói Mendes"},
	{"no":"Estiva", "concentrador":"Elói Mendes"},
	{"no":"Matias Cardoso", "concentrador":"Montes Claros"},
	{"no":"Rio Acima", "concentrador":"Belo Horizonte"},
	{"no":"Abre Campo", "concentrador":"Ipatinga"},
	{"no":"Malacacheta", "concentrador":"Ipatinga"},
	{"no":"Itapeva", "concentrador":"Elói Mendes"},
	{"no":"Manga", "concentrador":"Montes Claros"},
	{"no":"Coqueiral", "concentrador":"Elói Mendes"},
	{"no":"Bonfinópolis de Minas", "concentrador":"Presidente Olegário"},
	{"no":"Andrelândia", "concentrador":"Juiz de Fora"},
	{"no":"São Roque de Minas", "concentrador":"Betim"},
	{"no":"Pratápolis", "concentrador":"Elói Mendes"},
	{"no":"Pedralva", "concentrador":"Elói Mendes"},
	{"no":"Morada Nova de Minas", "concentrador":"Betim"},
	{"no":"Peçanha", "concentrador":"Ipatinga"},
	{"no":"Sabinópolis", "concentrador":"Ipatinga"},
	{"no":"São Tomás de Aquino", "concentrador":"Uberaba"},
	{"no":"Conceição dos Ouros", "concentrador":"Elói Mendes"},
	{"no":"Abadia dos Dourados", "concentrador":"Araguari"},
	{"no":"Santa Rita de Caldas", "concentrador":"Elói Mendes"},
	{"no":"Igaratinga", "concentrador":"Betim"},
	{"no":"Capitólio", "concentrador":"Betim"},
	{"no":"São João Evangelista", "concentrador":"Ipatinga"},
	{"no":"Entre Rios de Minas", "concentrador":"Belo Horizonte"},
	{"no":"Pouso Alto", "concentrador":"Elói Mendes"},
	{"no":"São João do Manhuaçu", "concentrador":"Ipatinga"},
	{"no":"Olhos-dÁgua", "concentrador":"Montes Claros"},
	{"no":"Carmo da Mata", "concentrador":"Betim"},
	{"no":"Varjão de MInas", "concentrador":"Presidente Olegário"},
	{"no":"São Gonçalo do Abaeté", "concentrador":"Presidente Olegário"},
	{"no":"Córrego Fundo", "concentrador":"Betim"},
	{"no":"Maria da Fé", "concentrador":"Elói Mendes"},
	{"no":"Congonhal", "concentrador":"Elói Mendes"},
	{"no":"Lagoa Dourada", "concentrador":"Belo Horizonte"},
	{"no":"União de Minas", "concentrador":"Uberaba"},
	{"no":"Ataléia", "concentrador":"Ipatinga"},
	{"no":"São Gonçalo do Pará", "concentrador":"Betim"},
	{"no":"Ipuiúna", "concentrador":"Elói Mendes"},
	{"no":"Jequeri", "concentrador":"Ipatinga"},
	{"no":"Caraí", "concentrador":"Ipatinga"},
	{"no":"Caetanópolis", "concentrador":"Belo Horizonte"},
	{"no":"Ressaquinha", "concentrador":"Belo Horizonte"},
	{"no":"Lagamar", "concentrador":"Presidente Olegário"},
	{"no":"Veríssimo", "concentrador":"Uberaba"},
	{"no":"Cristina", "concentrador":"Elói Mendes"},
	{"no":"Águas Vermelhas", "concentrador":"Montes Claros"},
	{"no":"Tarumirim", "concentrador":"Ipatinga"},
	{"no":"Campo do Meio", "concentrador":"Elói Mendes"},
	{"no":"Mar de Espanha", "concentrador":"Juiz de Fora"},
	{"no":"Raposos", "concentrador":"Belo Horizonte"},
	{"no":"Varzelândia", "concentrador":"Montes Claros"},
	{"no":"Mário Campos", "concentrador":"Betim"},
	{"no":"São José da Varginha", "concentrador":"Betim"},
	{"no":"Água Boa", "concentrador":"Ipatinga"},
	{"no":"Gurinhatã", "concentrador":"Araguari"},
	{"no":"Piranga", "concentrador":"Belo Horizonte"},
	{"no":"São Brás do Suaçuí", "concentrador":"Belo Horizonte"},
	{"no":"São Tiago", "concentrador":"Betim"},
	{"no":"Comendador Gomes", "concentrador":"Uberaba"},
	{"no":"Guarani", "concentrador":"Juiz de Fora"},
	{"no":"Bueno Brandão", "concentrador":"Elói Mendes"},
	{"no":"Ipaba", "concentrador":"Ipatinga"},
	{"no":"Guimarânia", "concentrador":"Presidente Olegário"},
	{"no":"Padre Paraíso", "concentrador":"Ipatinga"},
	{"no":"Serra dos Aimorés", "concentrador":"Ipatinga"},
	{"no":"Santa Maria de Itabira", "concentrador":"Belo Horizonte"},
	{"no":"Poté", "concentrador":"Ipatinga"},
	{"no":"Bom Jesus do Galho", "concentrador":"Ipatinga"},
	{"no":"Capetinga", "concentrador":"Uberaba"},
	{"no":"Miradouro", "concentrador":"Juiz de Fora"},
	{"no":"Perdigão", "concentrador":"Betim"},
	{"no":"Santa Maria do Suaçuí", "concentrador":"Ipatinga"},
	{"no":"Serrania", "concentrador":"Elói Mendes"},
	{"no":"São Pedro dos Ferros", "concentrador":"Ipatinga"},
	{"no":"São Vicente de Minas", "concentrador":"Juiz de Fora"},
	{"no":"Montalvânia", "concentrador":"Montes Claros"},
	{"no":"Araújos", "concentrador":"Betim"},
	{"no":"Padre Carvalho", "concentrador":"Montes Claros"},
	{"no":"Turvolândia", "concentrador":"Elói Mendes"},
	{"no":"Gouveia", "concentrador":"Belo Horizonte"},
	{"no":"Jacuí", "concentrador":"Elói Mendes"},
	{"no":"São Geraldo", "concentrador":"Juiz de Fora"},
	{"no":"Eugenópolis", "concentrador":"Juiz de Fora"},
	{"no":"Medeiros", "concentrador":"Betim"},
	{"no":"São Pedro da União", "concentrador":"Elói Mendes"},
	{"no":"Nova Porteirinha", "concentrador":"Montes Claros"},
	{"no":"Belo Vale", "concentrador":"Belo Horizonte"},
	{"no":"Teixeiras", "concentrador":"Belo Horizonte"},
	{"no":"Resende Costa", "concentrador":"Belo Horizonte"},
	{"no":"Maravilhas", "concentrador":"Betim"},
	{"no":"Martins Soares", "concentrador":"Ipatinga"},
	{"no":"Virgínia", "concentrador":"Elói Mendes"},
	{"no":"Ladainha", "concentrador":"Ipatinga"},
	{"no":"Bom Jesus da Penha", "concentrador":"Elói Mendes"},
	{"no":"São Romão", "concentrador":"Montes Claros"},
	{"no":"Itanhomi", "concentrador":"Ipatinga"},
	{"no":"Joaíma", "concentrador":"Ipatinga"},
	{"no":"Piraúba", "concentrador":"Juiz de Fora"},
	{"no":"Ubaporanga", "concentrador":"Ipatinga"},
	{"no":"Buenópolis", "concentrador":"Montes Claros"},
	{"no":"Prados", "concentrador":"Belo Horizonte"},
	{"no":"Ferros", "concentrador":"Ipatinga"},
	{"no":"Urucuia", "concentrador":"Montes Claros"},
	{"no":"Santana do Manhuaçu", "concentrador":"Ipatinga"},
	{"no":"Virginópolis", "concentrador":"Ipatinga"},
	{"no":"Arapuá", "concentrador":"Presidente Olegário"},
	{"no":"Carbonita", "concentrador":"Montes Claros"},
	{"no":"Silvianópolis", "concentrador":"Elói Mendes"},
	{"no":"Chapada Gaúcha", "concentrador":"Montes Claros"},
	{"no":"Prudente de Morais", "concentrador":"Belo Horizonte"},
	{"no":"Guiricema", "concentrador":"Juiz de Fora"},
	{"no":"Itinga", "concentrador":"Montes Claros"},
	{"no":"Claraval", "concentrador":"Uberaba"},
	{"no":"Caparaó", "concentrador":"Ipatinga"},
	{"no":"Albertina", "concentrador":"Elói Mendes"},
	{"no":"Inhaúma", "concentrador":"Belo Horizonte"},
	{"no":"Braúnas", "concentrador":"Ipatinga"},
	{"no":"Jacinto", "concentrador":"Montes Claros"},
	{"no":"Alto Jequitibá", "concentrador":"Ipatinga"},
	{"no":"Fervedouro", "concentrador":"Ipatinga"},
	{"no":"Baldim", "concentrador":"Belo Horizonte"},
	{"no":"Durandé", "concentrador":"Ipatinga"},
	{"no":"Pedrinópolis", "concentrador":"Uberaba"},
	{"no":"Tombos", "concentrador":"Juiz de Fora"},
	{"no":"Alto Rio Doce", "concentrador":"Juiz de Fora"},
	{"no":"Mercês", "concentrador":"Juiz de Fora"},
	{"no":"Rio Vermelho", "concentrador":"Ipatinga"},
	{"no":"Capim Branco", "concentrador":"Belo Horizonte"},
	{"no":"Antônio Dias", "concentrador":"Ipatinga"},
	{"no":"Verdelândia", "concentrador":"Montes Claros"},
	{"no":"Bom Repouso", "concentrador":"Elói Mendes"},
	{"no":"Heliodora", "concentrador":"Elói Mendes"},
	{"no":"Guaraciama", "concentrador":"Montes Claros"},
	{"no":"Mato Verde", "concentrador":"Montes Claros"},
	{"no":"Careaçu", "concentrador":"Elói Mendes"},
	{"no":"Engenheiro Caldas", "concentrador":"Ipatinga"},
	{"no":"Sericita", "concentrador":"Ipatinga"},
	{"no":"Itamarati de Minas", "concentrador":"Juiz de Fora"},
	{"no":"Piedade do Rio Grande", "concentrador":"Juiz de Fora"},
	{"no":"Virgem da Lapa", "concentrador":"Montes Claros"},
	{"no":"Francisco Dumont", "concentrador":"Montes Claros"},
	{"no":"Itaipé", "concentrador":"Ipatinga"},
	{"no":"Cordisburgo", "concentrador":"Belo Horizonte"},
	{"no":"Recreio", "concentrador":"Juiz de Fora"},
	{"no":"Piracema", "concentrador":"Betim"},
	{"no":"Mirabela", "concentrador":"Montes Claros"},
	{"no":"Rio Novo", "concentrador":"Juiz de Fora"},
	{"no":"Caputira", "concentrador":"Ipatinga"},
	{"no":"Sapucaí-Mirim", "concentrador":"Elói Mendes"},
	{"no":"Madre de Deus de Minas", "concentrador":"Juiz de Fora"},
	{"no":"Paula Cândido", "concentrador":"Juiz de Fora"},
	{"no":"Itabirinha de Mantena", "concentrador":"Ipatinga"},
	{"no":"Santa Rita do Itueto", "concentrador":"Ipatinga"},
	{"no":"Tiradentes", "concentrador":"Belo Horizonte"},
	{"no":"São João da Lagoa", "concentrador":"Montes Claros"},
	{"no":"Engenheiro Navarro", "concentrador":"Montes Claros"},
	{"no":"Angelândia", "concentrador":"Ipatinga"},
	{"no":"Florestal", "concentrador":"Betim"},
	{"no":"Santo Antônio do Jacinto", "concentrador":"Montes Claros"},
	{"no":"Guidoval", "concentrador":"Juiz de Fora"},
	{"no":"Rubim", "concentrador":"Ipatinga"},
	{"no":"Jequitibá", "concentrador":"Belo Horizonte"},
	{"no":"São Francisco de Paula", "concentrador":"Betim"},
	{"no":"Luisburgo", "concentrador":"Ipatinga"},
	{"no":"Josenópolis", "concentrador":"Montes Claros"},
	{"no":"Berilo", "concentrador":"Montes Claros"},
	{"no":"Porto Firme", "concentrador":"Belo Horizonte"},
	{"no":"Salto da Divisa", "concentrador":"Montes Claros"},
	{"no":"Pratinha", "concentrador":"Uberaba"},
	{"no":"Iapu", "concentrador":"Ipatinga"},
	{"no":"Frei Inocêncio", "concentrador":"Ipatinga"},
	{"no":"Chapada do Norte", "concentrador":"Montes Claros"},
	{"no":"Santana de Pirapama", "concentrador":"Belo Horizonte"},
	{"no":"São Sebastião da Bela Vista", "concentrador":"Elói Mendes"},
	{"no":"Riachinho", "concentrador":"Presidente Olegário"},
	{"no":"Senhora dos Remédios", "concentrador":"Belo Horizonte"},
	{"no":"Camacho", "concentrador":"Betim"},
	{"no":"Coimbra", "concentrador":"Juiz de Fora"},
	{"no":"Divisa Nova", "concentrador":"Elói Mendes"},
	{"no":"São Thomé das Letras", "concentrador":"Elói Mendes"},
	{"no":"Bonfim", "concentrador":"Betim"},
	{"no":"Cruzeiro da Fortaleza", "concentrador":"Presidente Olegário"},
	{"no":"Piranguinho", "concentrador":"Elói Mendes"},
	{"no":"Aiuruoca", "concentrador":"Elói Mendes"},
	{"no":"Moema", "concentrador":"Betim"},
	{"no":"Pocrane", "concentrador":"Ipatinga"},
	{"no":"Araponga", "concentrador":"Juiz de Fora"},
	{"no":"Coroaci", "concentrador":"Ipatinga"},
	{"no":"Natércia", "concentrador":"Elói Mendes"},
	{"no":"Botumirim", "concentrador":"Montes Claros"},
	{"no":"Ipiaçu", "concentrador":"Araguari"},
	{"no":"Pedra do Indaiá", "concentrador":"Betim"},
	{"no":"Cachoeira de Pajeú", "concentrador":"Montes Claros"},
	{"no":"Inconfidentes", "concentrador":"Elói Mendes"},
	{"no":"Santa Bárbara do Leste", "concentrador":"Ipatinga"},
	{"no":"Ibiaí", "concentrador":"Montes Claros"},
	{"no":"Claro dos Poções", "concentrador":"Montes Claros"},
	{"no":"Munhoz", "concentrador":"Elói Mendes"},
	{"no":"Ubaí", "concentrador":"Montes Claros"},
	{"no":"Alto Caparaó", "concentrador":"Ipatinga"},
	{"no":"São João do Oriente", "concentrador":"Ipatinga"},
	{"no":"Pedras de Maria da Cruz", "concentrador":"Montes Claros"},
	{"no":"Bom Jardim de Minas", "concentrador":"Juiz de Fora"},
	{"no":"Reduto", "concentrador":"Ipatinga"},
	{"no":"Jordânia", "concentrador":"Montes Claros"},
	{"no":"Ninheira", "concentrador":"Montes Claros"},
	{"no":"Santa Rita de Minas", "concentrador":"Ipatinga"},
	{"no":"Açucena", "concentrador":"Ipatinga"},
	{"no":"Alfredo Vasconcelos", "concentrador":"Juiz de Fora"},
	{"no":"Delfim Moreira", "concentrador":"Elói Mendes"},
	{"no":"Inimutaba", "concentrador":"Belo Horizonte"},
	{"no":"Paineiras", "concentrador":"Betim"},
	{"no":"Galiléia", "concentrador":"Ipatinga"},
	{"no":"Periquito", "concentrador":"Ipatinga"},
	{"no":"Augusto de Lima", "concentrador":"Montes Claros"},
	{"no":"Pavão", "concentrador":"Ipatinga"},
	{"no":"Piedade de Caratinga", "concentrador":"Ipatinga"},
	{"no":"Guaraciaba", "concentrador":"Belo Horizonte"},
	{"no":"Jequitaí", "concentrador":"Montes Claros"},
	{"no":"São Sebastião do Maranhão", "concentrador":"Ipatinga"},
	{"no":"São Miguel do Anta", "concentrador":"Juiz de Fora"},
	{"no":"Icaraí de Minas", "concentrador":"Montes Claros"},
	{"no":"Dona Eusébia", "concentrador":"Juiz de Fora"},
	{"no":"Riacho dos Machados", "concentrador":"Montes Claros"},
	{"no":"Ponto dos Volantes", "concentrador":"Ipatinga"},
	{"no":"Pedra Bonita", "concentrador":"Ipatinga"},
	{"no":"Divisópolis", "concentrador":"Montes Claros"},
	{"no":"Santa Rosa da Serra", "concentrador":"Presidente Olegário"},
	{"no":"Patrocínio do Muriaé", "concentrador":"Juiz de Fora"},
	{"no":"Itueta", "concentrador":"Ipatinga"},
	{"no":"Coronel Murta", "concentrador":"Montes Claros"},
	{"no":"Palma", "concentrador":"Juiz de Fora"},
	{"no":"Senador Firmino", "concentrador":"Juiz de Fora"},
	{"no":"Alpercata", "concentrador":"Ipatinga"},
	{"no":"Japaraíba", "concentrador":"Betim"},
	{"no":"Matutina", "concentrador":"Presidente Olegário"},
	{"no":"Laranjal", "concentrador":"Juiz de Fora"},
	{"no":"Novo Oriente de Minas", "concentrador":"Ipatinga"},
	{"no":"Central de Minas", "concentrador":"Ipatinga"},
	{"no":"Luminárias", "concentrador":"Elói Mendes"},
	{"no":"Coluna", "concentrador":"Ipatinga"},
	{"no":"Itutinga", "concentrador":"Elói Mendes"},
	{"no":"Dionísio", "concentrador":"Ipatinga"},
	{"no":"Espírito Santo do Dourado", "concentrador":"Elói Mendes"},
	{"no":"Liberdade", "concentrador":"Juiz de Fora"},
	{"no":"Santa Cruz de Minas", "concentrador":"Belo Horizonte"},
	{"no":"Itacambira", "concentrador":"Montes Claros"},
	{"no":"Veredinha", "concentrador":"Montes Claros"},
	{"no":"Imbé de Minas", "concentrador":"Ipatinga"},
	{"no":"Pequi", "concentrador":"Betim"},
	{"no":"Cana Verde", "concentrador":"Elói Mendes"},
	{"no":"Divisa Alegre", "concentrador":"Montes Claros"},
	{"no":"Indaiabira", "concentrador":"Montes Claros"},
	{"no":"Dom Silvério", "concentrador":"Belo Horizonte"},
	{"no":"Cristiano Otoni", "concentrador":"Belo Horizonte"},
	{"no":"Comercinho", "concentrador":"Montes Claros"},
	{"no":"Senador Amaral", "concentrador":"Elói Mendes"},
	{"no":"Cachoeira Dourada", "concentrador":"Araguari"},
	{"no":"Setubinha", "concentrador":"Montes Claros"},
	{"no":"Quartel Geral", "concentrador":"Betim"},
	{"no":"São João das Missões", "concentrador":"Montes Claros"},
	{"no":"Cascalho Rico", "concentrador":"Araguari"},
	{"no":"Machacalis", "concentrador":"Ipatinga"},
	{"no":"Carrancas", "concentrador":"Elói Mendes"},
	{"no":"Ribeirão Vermelho", "concentrador":"Elói Mendes"},
	{"no":"Volta Grande", "concentrador":"Juiz de Fora"},
	{"no":"Ibertioga", "concentrador":"Juiz de Fora"},
	{"no":"Santana do Jacaré", "concentrador":"Betim"},
	{"no":"São Sebastião do Anta", "concentrador":"Ipatinga"},
	{"no":"Rio Manso", "concentrador":"Betim"},
	{"no":"Joanésia", "concentrador":"Ipatinga"},
	{"no":"Barra Longa", "concentrador":"Belo Horizonte"},
	{"no":"Córrego Danta", "concentrador":"Betim"},
	{"no":"Estrela do Indaiá", "concentrador":"Betim"},
	{"no":"Itumirim", "concentrador":"Elói Mendes"},
	{"no":"Dom Bosco", "concentrador":"Presidente Olegário"},
	{"no":"Nova União", "concentrador":"Belo Horizonte"},
	{"no":"São Domingos das Dores", "concentrador":"Ipatinga"},
	{"no":"Chalé", "concentrador":"Ipatinga"},
	{"no":"Orizânia", "concentrador":"Ipatinga"},
	{"no":"Jesuânia", "concentrador":"Elói Mendes"},
	{"no":"Desterro de Entre Rios", "concentrador":"Betim"},
	{"no":"Jaguaraçu", "concentrador":"Ipatinga"},
	{"no":"Onça de Pitangui", "concentrador":"Betim"},
	{"no":"Francisco Badaró", "concentrador":"Montes Claros"},
	{"no":"Soledade de Minas", "concentrador":"Elói Mendes"},
	{"no":"São Bento Abade", "concentrador":"Elói Mendes"},
	{"no":"Mendes Pimentel", "concentrador":"Ipatinga"},
	{"no":"Cajuri", "concentrador":"Juiz de Fora"},
	{"no":"Rubelita", "concentrador":"Montes Claros"},
	{"no":"Rio Preto", "concentrador":"Juiz de Fora"},
	{"no":"Bandeira do Sul", "concentrador":"Elói Mendes"},
	{"no":"Bonito de Minas", "concentrador":"Montes Claros"},
	{"no":"Cristália", "concentrador":"Montes Claros"},
	{"no":"Mata Verde", "concentrador":"Montes Claros"},
	{"no":"Piranguçu", "concentrador":"Elói Mendes"},
	{"no":"Caiana", "concentrador":"Ipatinga"},
	{"no":"Ritápolis", "concentrador":"Belo Horizonte"},
	{"no":"Lagoa dos Patos", "concentrador":"Montes Claros"},
	{"no":"Aguanil", "concentrador":"Elói Mendes"},
	{"no":"São João do Manteninha", "concentrador":"Ipatinga"},
	{"no":"Tumiritinga", "concentrador":"Ipatinga"},
	{"no":"Tapiraí", "concentrador":"Betim"},
	{"no":"Crisólita", "concentrador":"Ipatinga"},
	{"no":"Morro da Garça", "concentrador":"Belo Horizonte"},
	{"no":"Santa Rita de Jacutinga", "concentrador":"Juiz de Fora"},
	{"no":"Ingaí", "concentrador":"Elói Mendes"},
	{"no":"Crucilândia", "concentrador":"Betim"},
	{"no":"Frei Gaspar", "concentrador":"Ipatinga"},
	{"no":"Descoberto", "concentrador":"Juiz de Fora"},
	{"no":"Santo Antônio do Grama", "concentrador":"Ipatinga"},
	{"no":"Bom Jesus do Amparo", "concentrador":"Belo Horizonte"},
	{"no":"Alvorada de Minas", "concentrador":"Belo Horizonte"},
	{"no":"Senhora de Oliveira", "concentrador":"Belo Horizonte"},
	{"no":"Cordislândia", "concentrador":"Elói Mendes"},
	{"no":"Piedade de Ponte Nova", "concentrador":"Ipatinga"},
	{"no":"Santa Cruz do Escalvado", "concentrador":"Ipatinga"},
	{"no":"Lontra", "concentrador":"Montes Claros"},
	{"no":"Vargem Alegre", "concentrador":"Ipatinga"},
	{"no":"Naque", "concentrador":"Ipatinga"},
	{"no":"Pintópolis", "concentrador":"Montes Claros"},
	{"no":"Sobrália", "concentrador":"Ipatinga"},
	{"no":"Santo Hipólito", "concentrador":"Belo Horizonte"},
	{"no":"Franciscópolis", "concentrador":"Ipatinga"},
	{"no":"São Francisco do Glória", "concentrador":"Juiz de Fora"},
	{"no":"Vermelho Novo", "concentrador":"Ipatinga"},
	{"no":"São Pedro do Suaçuí", "concentrador":"Ipatinga"},
	{"no":"Canaã", "concentrador":"Ipatinga"},
	{"no":"São José do Jacuri", "concentrador":"Ipatinga"},
	{"no":"Juramento", "concentrador":"Montes Claros"},
	{"no":"Japonvar", "concentrador":"Montes Claros"},
	{"no":"Barão de Monte Alto", "concentrador":"Juiz de Fora"},
	{"no":"Toledo", "concentrador":"Elói Mendes"},
	{"no":"Montezuma", "concentrador":"Montes Claros"},
	{"no":"Divinolândia de Minas", "concentrador":"Ipatinga"},
	{"no":"Virgolândia", "concentrador":"Ipatinga"},
	{"no":"Taquaraçu de Minas", "concentrador":"Belo Horizonte"},
	{"no":"Curral de Dentro", "concentrador":"Montes Claros"},
	{"no":"Belmiro Braga", "concentrador":"Juiz de Fora"},
	{"no":"Presidente Juscelino", "concentrador":"Belo Horizonte"},
	{"no":"Felisburgo", "concentrador":"Ipatinga"},
	{"no":"São José do Goiabal", "concentrador":"Ipatinga"},
	{"no":"Carvalhópolis", "concentrador":"Elói Mendes"},
	{"no":"Moeda", "concentrador":"Belo Horizonte"},
	{"no":"Oratórios", "concentrador":"Ipatinga"},
	{"no":"Minduri", "concentrador":"Juiz de Fora"},
	{"no":"Conceição das Pedras", "concentrador":"Elói Mendes"},
	{"no":"Dores de Guanhães", "concentrador":"Ipatinga"},
	{"no":"Joaquim Felício", "concentrador":"Montes Claros"},
	{"no":"Ibitiúra de Minas", "concentrador":"Elói Mendes"},
	{"no":"Piedade dos Gerais", "concentrador":"Betim"},
	{"no":"Dom Cavati", "concentrador":"Ipatinga"},
	{"no":"Datas", "concentrador":"Belo Horizonte"},
	{"no":"Juvenília", "concentrador":"Montes Claros"},
	{"no":"Faria Lemos", "concentrador":"Juiz de Fora"},
	{"no":"José Raydan", "concentrador":"Ipatinga"},
	{"no":"Divino das Laranjeiras", "concentrador":"Ipatinga"},
	{"no":"Santa Bárbara do Tugúrio", "concentrador":"Juiz de Fora"},
	{"no":"São João da Mata", "concentrador":"Elói Mendes"},
	{"no":"Palmópolis", "concentrador":"Ipatinga"},
	{"no":"Funilândia", "concentrador":"Belo Horizonte"},
	{"no":"Cônego Marinho", "concentrador":"Montes Claros"},
	{"no":"Cuparaque", "concentrador":"Ipatinga"},
	{"no":"Vieiras", "concentrador":"Juiz de Fora"},
	{"no":"Santo Antônio do Retiro", "concentrador":"Montes Claros"},
	{"no":"Entre Folhas", "concentrador":"Ipatinga"},
	{"no":"Piau", "concentrador":"Juiz de Fora"},
	{"no":"Biquinhas", "concentrador":"Betim"},
	{"no":"Carvalhos", "concentrador":"Juiz de Fora"},
	{"no":"Catuji", "concentrador":"Ipatinga"},
	{"no":"Goianá", "concentrador":"Juiz de Fora"},
	{"no":"Gonzaga", "concentrador":"Ipatinga"},
	{"no":"Jampruca", "concentrador":"Ipatinga"},
	{"no":"Ibituruna", "concentrador":"Betim"},
	{"no":"Nova Belém", "concentrador":"Ipatinga"},
	{"no":"Cipotânea", "concentrador":"Belo Horizonte"},
	{"no":"Mesquita", "concentrador":"Ipatinga"},
	{"no":"Gameleiras", "concentrador":"Montes Claros"},
	{"no":"Ouro Verde de Minas", "concentrador":"Ipatinga"},
	{"no":"Itaverava", "concentrador":"Belo Horizonte"},
	{"no":"Luislândia", "concentrador":"Montes Claros"},
	{"no":"Sardoá", "concentrador":"Ipatinga"},
	{"no":"Tabuleiro", "concentrador":"Juiz de Fora"},
	{"no":"Nova Módica", "concentrador":"Ipatinga"},
	{"no":"Coronel Xavier Chaves", "concentrador":"Belo Horizonte"},
	{"no":"Capitão Andrade", "concentrador":"Ipatinga"},
	{"no":"Rio Espera", "concentrador":"Belo Horizonte"},
	{"no":"Marilac", "concentrador":"Ipatinga"},
	{"no":"Jenipapo de Minas", "concentrador":"Montes Claros"},
	{"no":"Uruana de Minas", "concentrador":"Presidente Olegário"},
	{"no":"Rosário da Limeira", "concentrador":"Juiz de Fora"},
	{"no":"Materlândia", "concentrador":"Ipatinga"},
	{"no":"Conceição da Barra de Minas", "concentrador":"Betim"},
	{"no":"Gonçalves", "concentrador":"Elói Mendes"},
	{"no":"Conceição de Ipanema", "concentrador":"Ipatinga"},
	{"no":"Guarará", "concentrador":"Juiz de Fora"},
	{"no":"Leandro Ferreira", "concentrador":"Betim"},
	{"no":"Pescador", "concentrador":"Ipatinga"},
	{"no":"Felício dos Santos", "concentrador":"Montes Claros"},
	{"no":"Bocaina de Minas", "concentrador":"Juiz de Fora"},
	{"no":"Presidente Bernardes", "concentrador":"Belo Horizonte"},
	{"no":"Rio do Prado", "concentrador":"Ipatinga"},
	{"no":"Dores do Turvo", "concentrador":"Juiz de Fora"},
	{"no":"Fama", "concentrador":"Elói Mendes"},
	{"no":"Alvarenga", "concentrador":"Ipatinga"},
	{"no":"Santa Rita de Ibitipoca", "concentrador":"Juiz de Fora"},
	{"no":"Capela Nova", "concentrador":"Belo Horizonte"},
	{"no":"Pai Pedro", "concentrador":"Montes Claros"},
	{"no":"São José do Alegre", "concentrador":"Elói Mendes"},
	{"no":"Dom Joaquim", "concentrador":"Belo Horizonte"},
	{"no":"Natalândia", "concentrador":"Presidente Olegário"},
	{"no":"Santa Helena de Minas", "concentrador":"Ipatinga"},
	{"no":"Ibiracatu", "concentrador":"Montes Claros"},
	{"no":"Amparo do Serra", "concentrador":"Belo Horizonte"},
	{"no":"Patis", "concentrador":"Montes Claros"},
	{"no":"São José do Divino", "concentrador":"Ipatinga"},
	{"no":"Paulistas", "concentrador":"Ipatinga"},
	{"no":"São Sebastião da Vargem Alegre", "concentrador":"Juiz de Fora"},
	{"no":"Santana do Riacho", "concentrador":"Belo Horizonte"},
	{"no":"Campanário", "concentrador":"Ipatinga"},
	{"no":"Araçaí", "concentrador":"Belo Horizonte"},
	{"no":"São Geraldo da Piedade", "concentrador":"Ipatinga"},
	{"no":"Couto de Magalhães de Minas", "concentrador":"Montes Claros"},
	{"no":"Mamonas", "concentrador":"Montes Claros"},
	{"no":"Bandeira", "concentrador":"Montes Claros"},
	{"no":"Bertópolis", "concentrador":"Ipatinga"},
	{"no":"São João do Pacuí", "concentrador":"Montes Claros"},
	{"no":"Senador Modestino Gonçalves", "concentrador":"Montes Claros"},
	{"no":"Cachoeira da Prata", "concentrador":"Belo Horizonte"},
	{"no":"Pequeri", "concentrador":"Juiz de Fora"},
	{"no":"Vargem Bonita", "concentrador":"Betim"},
	{"no":"Novorizonte", "concentrador":"Montes Claros"},
	{"no":"Morro do Pilar", "concentrador":"Belo Horizonte"},
	{"no":"Fruta de Leite", "concentrador":"Montes Claros"},
	{"no":"Santa Maria do Salto", "concentrador":"Montes Claros"},
	{"no":"Cantagalo", "concentrador":"Ipatinga"},
	{"no":"Brás Pires", "concentrador":"Belo Horizonte"},
	{"no":"Aricanduva", "concentrador":"Ipatinga"},
	{"no":"Santana do Deserto", "concentrador":"Juiz de Fora"},
	{"no":"Leme do Prado", "concentrador":"Montes Claros"},
	{"no":"Santo Antônio do Itambé", "concentrador":"Belo Horizonte"},
	{"no":"Fortuna de Minas", "concentrador":"Belo Horizonte"},
	{"no":"Congonhas do Norte", "concentrador":"Belo Horizonte"},
	{"no":"Ponto Chique", "concentrador":"Montes Claros"},
	{"no":"Vargem Grande do Rio Pardo", "concentrador":"Montes Claros"},
	{"no":"Bias Fortes", "concentrador":"Juiz de Fora"},
	{"no":"Santa Fé de Minas", "concentrador":"Montes Claros"},
	{"no":"Santo Antônio do Aventureiro", "concentrador":"Juiz de Fora"},
	{"no":"Simão Pereira", "concentrador":"Juiz de Fora"},
	{"no":"Olímpio Noronha", "concentrador":"Elói Mendes"},
	{"no":"Diogo de Vasconcelos", "concentrador":"Belo Horizonte"},
	{"no":"Catuti", "concentrador":"Montes Claros"},
	{"no":"Monjolos", "concentrador":"Belo Horizonte"},
	{"no":"Douradoquara", "concentrador":"Araguari"},
	{"no":"Marliéria", "concentrador":"Ipatinga"},
	{"no":"Tocos do Moji", "concentrador":"Elói Mendes"},
	{"no":"São Geraldo do Baixio", "concentrador":"Ipatinga"},
	{"no":"Argirita", "concentrador":"Juiz de Fora"},
	{"no":"Fronteira dos Vales", "concentrador":"Ipatinga"},
	{"no":"Pingo-dÁgua", "concentrador":"Ipatinga"},
	{"no":"Córrego do Bom Jesus", "concentrador":"Elói Mendes"},
	{"no":"Coronel Pacheco", "concentrador":"Juiz de Fora"},
	{"no":"Acaiaca", "concentrador":"Belo Horizonte"},
	{"no":"Santa Bárbara do Monte Verde", "concentrador":"Juiz de Fora"},
	{"no":"Santa Cruz de Salinas", "concentrador":"Montes Claros"},
	{"no":"Divinésia", "concentrador":"Juiz de Fora"},
	{"no":"Santa Efigênia de Minas", "concentrador":"Ipatinga"},
	{"no":"Fernandes Tourinho", "concentrador":"Ipatinga"},
	{"no":"Goiabeira", "concentrador":"Ipatinga"},
	{"no":"São Félix de Minas", "concentrador":"Ipatinga"},
	{"no":"Taparuba", "concentrador":"Ipatinga"},
	{"no":"Santana de Cataguases", "concentrador":"Juiz de Fora"},
	{"no":"São José da Safira", "concentrador":"Ipatinga"},
	{"no":"Berizal", "concentrador":"Montes Claros"},
	{"no":"Glaucilândia", "concentrador":"Montes Claros"},
	{"no":"Mathias Lobato", "concentrador":"Ipatinga"},
	{"no":"Maripá de Minas", "concentrador":"Juiz de Fora"},
	{"no":"José Gonçalves de Minas", "concentrador":"Montes Claros"},
	{"no":"Desterro do Melo", "concentrador":"Juiz de Fora"},
	{"no":"Ewbank da Câmara", "concentrador":"Juiz de Fora"},
	{"no":"Pedra do Anta", "concentrador":"Ipatinga"},
	{"no":"Chácara", "concentrador":"Juiz de Fora"},
	{"no":"Chiador", "concentrador":"Juiz de Fora"},
	{"no":"Miravânia", "concentrador":"Montes Claros"},
	{"no":"Alagoa", "concentrador":"Juiz de Fora"},
	{"no":"Sem-Peixe", "concentrador":"Ipatinga"},
	{"no":"Senhora do Porto", "concentrador":"Ipatinga"},
	{"no":"Bugre", "concentrador":"Ipatinga"},
	{"no":"Campo Azul", "concentrador":"Montes Claros"},
	{"no":"Senador José Bento", "concentrador":"Elói Mendes"},
	{"no":"Serranópolis de Minas", "concentrador":"Montes Claros"},
	{"no":"Umburatiba", "concentrador":"Ipatinga"},
	{"no":"Serra Azul de Minas", "concentrador":"Ipatinga"},
	{"no":"Pedra Dourada", "concentrador":"Juiz de Fora"},
	{"no":"Córrego Novo", "concentrador":"Ipatinga"},
	{"no":"Santana dos Montes", "concentrador":"Belo Horizonte"},
	{"no":"São José do Mantimento", "concentrador":"Ipatinga"},
	{"no":"Lamim", "concentrador":"Belo Horizonte"},
	{"no":"Estrela Dalva", "concentrador":"Juiz de Fora"},
	{"no":"Marmelópolis", "concentrador":"Elói Mendes"},
	{"no":"Presidente Kubitschek", "concentrador":"Belo Horizonte"},
	{"no":"Dom Viçoso", "concentrador":"Elói Mendes"},
	{"no":"Doresópolis", "concentrador":"Betim"},
	{"no":"Frei Lagonegro", "concentrador":"Ipatinga"},
	{"no":"Caranaíba", "concentrador":"Belo Horizonte"},
	{"no":"Nacip Raydan", "concentrador":"Ipatinga"},
	{"no":"Rochedo de Minas", "concentrador":"Juiz de Fora"},
	{"no":"Arantina", "concentrador":"Juiz de Fora"},
	{"no":"São Gonçalo do Rio Preto", "concentrador":"Montes Claros"},
	{"no":"Wenceslau Braz", "concentrador":"Elói Mendes"},
	{"no":"Monte Formoso", "concentrador":"Ipatinga"},
	{"no":"Rio Doce", "concentrador":"Ipatinga"},
	{"no":"Serranos", "concentrador":"Juiz de Fora"},
	{"no":"Casa Grande", "concentrador":"Belo Horizonte"},
	{"no":"Silveirânia", "concentrador":"Juiz de Fora"},
	{"no":"São Sebastião do Rio Verde", "concentrador":"Elói Mendes"},
	{"no":"Queluzito", "concentrador":"Belo Horizonte"},
	{"no":"Oliveira Fortes", "concentrador":"Juiz de Fora"},
	{"no":"Passa-Vinte", "concentrador":"Juiz de Fora"},
	{"no":"Grupiara", "concentrador":"Araguari"},
	{"no":"Aracitaba", "concentrador":"Juiz de Fora"},
	{"no":"Catas Altas da Noruega", "concentrador":"Belo Horizonte"},
	{"no":"Santana do Garambéu", "concentrador":"Juiz de Fora"},
	{"no":"Seritinga", "concentrador":"Juiz de Fora"},
	{"no":"Olaria", "concentrador":"Juiz de Fora"},
	{"no":"Carmésia", "concentrador":"Ipatinga"},
	{"no":"Senador Cortes", "concentrador":"Juiz de Fora"},
	{"no":"Santo Antônio do Rio Abaixo", "concentrador":"Belo Horizonte"},
	{"no":"Antônio Prado de Minas", "concentrador":"Juiz de Fora"},
	{"no":"Itambé do Mato Dentro", "concentrador":"Belo Horizonte"},
	{"no":"Pedro Teixeira", "concentrador":"Juiz de Fora"},
	{"no":"Paiva", "concentrador":"Juiz de Fora"},
	{"no":"Consolação", "concentrador":"Elói Mendes"},
	{"no":"Passabém", "concentrador":"Belo Horizonte"},
	{"no":"São Sebastião do Rio Preto", "concentrador":"Belo Horizonte"},
	{"no":"Cedro do Abaeté", "concentrador":"Betim"},
	{"no":"Serra da Saudade", "concentrador":"Presidente Olegário"}
] }